chrpa/__init__.py
chrpa/main/__init__.py
chrpa/main/processing.py
chrpa/tests/__init__.py
chrpa/tests/test_chrpa.py
chrpa-0.0.6.dist-info/METADATA
chrpa-0.0.6.dist-info/WHEEL
chrpa-0.0.6.dist-info/licenses/LICENSE
chrpa-0.0.6.dist-info/RECORD
