Metadata-Version: 2.1
Name: chrpa
Version: 0.0.6
Summary: Climate Hazards Return Period Analysis
Author-email: HM & GP <hmendo@sandia.gov>
License-File: LICENSE
Classifier: License :: OSI Approved :: MIT License
Classifier: Operating System :: OS Independent
Classifier: Programming Language :: Python :: 3
Requires-Python: >=3.10.8
